varicon_observability/__init__.py
varicon_observability/capture.py
varicon_observability/celery_helpers.py
varicon_observability/celery_instrumentation.py
varicon_observability/config.py
varicon_observability/django_middleware.py
varicon_observability/filters.py
varicon_observability/integrations.py
varicon_observability/log_processor.py
varicon_observability/logs.py
varicon_observability/metrics.py
varicon_observability/setup.py
varicon_observability/span_filter.py
varicon_observability/trace_filter.py
varicon_observability/traces.py
varicon_observability-1.0.3.dist-info/licenses/LICENSE
varicon_observability-1.0.3.dist-info/METADATA
varicon_observability-1.0.3.dist-info/WHEEL
varicon_observability-1.0.3.dist-info/top_level.txt
varicon_observability-1.0.3.dist-info/RECORD
