Metadata-Version: 2.4
Name: varicon-observability
Version: 1.0.3
Summary: Unified observability package for Varicon services - logs, traces, and metrics
Author-email: samir Thapa <samir.thapa@varicon.com.au>
License: MIT
Keywords: observability,logging,tracing,metrics,opentelemetry,signoz
Classifier: Development Status :: 4 - Beta
Classifier: Intended Audience :: Developers
Classifier: License :: OSI Approved :: MIT License
Classifier: Programming Language :: Python :: 3
Classifier: Programming Language :: Python :: 3.8
Classifier: Programming Language :: Python :: 3.9
Classifier: Programming Language :: Python :: 3.10
Classifier: Programming Language :: Python :: 3.11
Classifier: Topic :: Software Development :: Libraries :: Python Modules
Classifier: Topic :: System :: Logging
Classifier: Topic :: System :: Monitoring
Requires-Python: >=3.8
License-File: LICENSE
Requires-Dist: opentelemetry-api<2.0.0,>=1.24.0
Requires-Dist: opentelemetry-sdk<2.0.0,>=1.24.0
Requires-Dist: opentelemetry-exporter-otlp<2.0.0,>=1.24.0
Requires-Dist: opentelemetry-semantic-conventions<0.61b0,>=0.45b0
Provides-Extra: django
Requires-Dist: django>=3.2; extra == "django"
Requires-Dist: opentelemetry-instrumentation-django<0.61b0,>=0.45b0; extra == "django"
Requires-Dist: opentelemetry-instrumentation-psycopg2<0.61b0,>=0.45b0; extra == "django"
Requires-Dist: opentelemetry-instrumentation-asgi<0.61b0,>=0.45b0; extra == "django"
Provides-Extra: fastapi
Requires-Dist: fastapi>=0.100.0; extra == "fastapi"
Requires-Dist: opentelemetry-instrumentation-fastapi<0.61b0,>=0.45b0; extra == "fastapi"
Requires-Dist: opentelemetry-instrumentation-httpx<0.61b0,>=0.45b0; extra == "fastapi"
Provides-Extra: celery
Requires-Dist: celery>=5.0.0; extra == "celery"
Requires-Dist: opentelemetry-instrumentation-celery<0.61b0,>=0.45b0; extra == "celery"
Provides-Extra: full
Requires-Dist: django>=3.2; extra == "full"
Requires-Dist: fastapi>=0.100.0; extra == "full"
Requires-Dist: celery>=5.0.0; extra == "full"
Requires-Dist: opentelemetry-instrumentation-django<0.61b0,>=0.45b0; extra == "full"
Requires-Dist: opentelemetry-instrumentation-fastapi<0.61b0,>=0.45b0; extra == "full"
Requires-Dist: opentelemetry-instrumentation-celery<0.61b0,>=0.45b0; extra == "full"
Requires-Dist: opentelemetry-instrumentation-psycopg2<0.61b0,>=0.45b0; extra == "full"
Requires-Dist: opentelemetry-instrumentation-httpx<0.61b0,>=0.45b0; extra == "full"
Requires-Dist: opentelemetry-instrumentation-redis<0.61b0,>=0.45b0; extra == "full"
Requires-Dist: opentelemetry-instrumentation-requests<0.61b0,>=0.45b0; extra == "full"
Requires-Dist: opentelemetry-instrumentation-asgi<0.61b0,>=0.45b0; extra == "full"
Dynamic: license-file
